[{"item":"http://www.wikidata.org/entity/Q48861","itemLabel":"Institut Max-Planck d'astrophysique","latitude":"48.261111111111","longitude":"11.671666666667"},{"item":"http://www.wikidata.org/entity/Q66818737","itemLabel":"LabLab UG","latitude":"51.34","longitude":"12.37"},{"item":"http://www.wikidata.org/entity/Q69914257","itemLabel":"Raketenflugtechnisches Forschungsinstitut","latitude":"52.928257","longitude":"10.161517"},{"item":"http://www.wikidata.org/entity/Q62669101","itemLabel":"Forschungseinrichtung für experimentelle Medizin","latitude":"52.436587777778","longitude":"13.316963888889"},{"item":"http://www.wikidata.org/entity/Q1823963","itemLabel":"Liebig-Museum","latitude":"50.580839","longitude":"8.666196"},{"item":"http://www.wikidata.org/entity/Q30294855","itemLabel":"Halbleiterlabor der Max-Planck-Gesellschaft","latitude":"48.091626","longitude":"11.64948"},{"item":"http://www.wikidata.org/entity/Q16947218","itemLabel":"Q16947218","latitude":"50.3697","longitude":"8.7412"},{"item":"http://www.wikidata.org/entity/Q111608278","itemLabel":"AEG-Büro- und Laborgebäude","latitude":"52.542372257091","longitude":"13.383832252998"},{"item":"http://www.wikidata.org/entity/Q98585775","itemLabel":"Labor Dr.-Enders-Straße 65 in Hof (Saale) (D-4-64-000-280#7)","latitude":"50.321038223215","longitude":"11.895957036619"},{"item":"http://www.wikidata.org/entity/Q98623229","itemLabel":"Labor Günther-Scharowsky-Straße 1; Günther-Scharowsky-Straße 3 in Erlangen (D-5-62-000-1031#1)","latitude":"49.575771394417","longitude":"11.005713508464"},{"item":"http://www.wikidata.org/entity/Q64957559","itemLabel":"Felsenkeller Untergrundlabor","latitude":"51.02229","longitude":"13.70275"},{"item":"http://www.wikidata.org/entity/Q98650222","itemLabel":"Baudenkmal D-1-80-117-447 in Garmisch-Partenkirchen im Ortsteil Partenkirchen","latitude":"47.420731694081","longitude":"10.984689931426"},{"item":"http://www.wikidata.org/entity/Q98620690","itemLabel":"Labor Silbergasse 2 (D-5-74-112-113#4)","latitude":"49.384671103157","longitude":"11.357405883479"},{"item":"http://www.wikidata.org/entity/Q98585777","itemLabel":"Labor Brennerstraße 19 in Bamberg (D-4-61-000-63#4)","latitude":"49.904972846451","longitude":"10.896834255217"},{"item":"http://www.wikidata.org/entity/Q1414969","itemLabel":"Rosenau","latitude":"48.5389","longitude":"9.03022"},{"item":"http://www.wikidata.org/entity/Q2649130","itemLabel":"Allianz Zentrum für Technik","latitude":"48.219158","longitude":"11.66586"},{"item":"http://www.wikidata.org/entity/Q778208","itemLabel":"Forschungsreaktor München","latitude":"48.2658","longitude":"11.6742"}]